{
    "version": "1.0", 
    "description": "H.264/AAC for Playstation portable", 
    "author": {
        "name": "Daniel G. Taylor", 
        "email": "dan@programmer-art.org"
    }, 
    "default": "Normal", 
    "make": "Sony", 
    "presets": [
        {
            "vcodec": {
                "passes": [
                    "pass=qual quantizer=27 subme=4 threads=0"
                ], 
                "container": "ffmux_mp4", 
                "name": "x264enc", 
                "height": [
                    272, 
                    272
                ], 
                "width": [
                    480, 
                    480
                ], 
                "rate": [
                    1,
                    25
                ]
            }, 
            "container": "ffmux_mp4", 
            "name": "Low", 
            "extension": "mp4", 
            "acodec": {
                "passes": [
                    "bitrate=96000 profile=LC"
                ], 
                "container": "ffmux_mp4", 
                "name": "faac", 
                "depth": [
                    8, 
                    24
                ], 
                "channels": [
                    1, 
                    2
                ], 
                "width": [
                    8, 
                    24
                ], 
                "rate": [
                    48000,
                    48000
                ]
            }
        }, 
        {
            "vcodec": {
                "passes": [
                    "pass=qual quantizer=21 me=umh subme=6 ref=2 threads=0"
                ], 
                "container": "ffmux_mp4", 
                "name": "x264enc", 
                "height": [
                    272, 
                    272
                ], 
                "width": [
                    480, 
                    480
                ], 
                "rate": [
                    1,
                    30
                ]
            }, 
            "container": "ffmux_mp4", 
            "name": "Normal", 
            "extension": "mp4", 
            "acodec": {
                "passes": [
                    "bitrate=128000 profile=LC"
                ], 
                "container": "ffmux_mp4", 
                "name": "faac", 
                "depth": [
                    8, 
                    24
                ], 
                "channels": [
                    1, 
                    2
                ], 
                "width": [
                    8, 
                    24
                ], 
                "rate": [
                    48000,
                    48000
                ]
            }
        }
    ], 
    "model": "PSP", 
    "icon": "file://psp.svg"
}
